keyb_antirepeat.v
//                                                                                 
//_______________________________________________________________________________________
//                                                                                       |
//                                   MÓDULO ANTIREPEAT                                   |
//_______________________________________________________________________________________|
// *Descripción: Módulo orientado a habilitar el valor del decodificador solo con el     |
//                flanco ascendente del enable del antibounce                            |                                                                                       
//_______________________________________________________________________________________|
// *Entradas: -clk: señal de clock                                                       |
//            -reset: señal de reset                                                     |
//            -enable_filter: señal de enable del módulo antibounce                      |
//                                                                                       |
// *Salidas: -enable_real: señal que indica si el dato decodificado del decoder proviene |
//                de un dato estable                                                     |
//                                                                                       |                           
//_______________________________________________________________________________________|

module keyb_antirepeat(
        input enable_filter,
        input reset,
        input clk,
        output reg enable_real    
);

    reg [2:1] curr_state, next_state;

    // Asignacion de estados
    parameter [1:0] A = 1'b0;
    parameter [1:0] B = 1'b1;

    // Logica de proximo estado y salida (combinacional)
    // Recordar SIEMPRE definir el proximo estado Y TODAS las salidas 
    // para TODAS las combinaciones posibles de Entradas y Estado Actual
    // Recomendacion: usar if/else de tal manera que el else capture
    // todas las combinaciones que no son explicitas
    always @(enable_filter, curr_state) begin
        case (curr_state)
            A: if (enable_filter)
                begin
                    enable_real <= 1;  
                    next_state <= B;
                end
               else
                begin
                    enable_real <= 0;
                    next_state <= A;
                end
            B: if (enable_filter)
                begin
                    enable_real <= 0;
                    next_state <= B;
                end
               else
                begin
                    enable_real <= 0; 
                    next_state <= A;
                end
        endcase
    end
    //Transicion de estado
    always @(posedge clk) begin
        if (reset == 1) begin     // Reset activo en alto
        curr_state <= A;
        end  // Estado inicial
        else begin
        curr_state <= next_state;  // Avanza al siguiente estado
        end
    end

endmodule

testbench_antirepeat.v
`timescale 1ns/1ps

module tb_keyb_antirepeat();

    reg clk;
    reg reset;
    reg enable_filter;
    wire enable_real;

    // Instancia del módulo bajo prueba (DUT)
    keyb_antirepeat dut (
        .clk(clk),
        .reset(reset),
        .enable_filter(enable_filter),
        .enable_real(enable_real)
    );

    // Generador de clock: 10 ns de período (100 MHz)
    initial clk = 0;
    always #5 clk = ~clk;

    initial begin
        // Configuración para generar el archivo .vcd
        $dumpfile("keyb_antirepeat.vcd");  // Nombre del archivo VCD
        $dumpvars(0, tb_keyb_antirepeat);  // Volcar todas las señales de este módulo y submódulos

        // Monitor en consola (opcional)
        $display("Tiempo\tclk\treset\ten_filter\ten_real");
        $monitor("%0dns\t%b\t%b\t%b\t\t%b", $time, clk, reset, enable_filter, enable_real);

        // Inicialización
        reset = 1;
        enable_filter = 0;

        // Tiempo de reset
        #15;
        reset = 0;

        // Esperar un poco en estado inicial
        #20;

        // Flanco ascendente
        enable_filter = 1;
        #20;

        // Mantener en alto
        #40;

        // Flanco descendente
        enable_filter = 0;
        #20;

        // Segundo flanco ascendente
        enable_filter = 1;
        #20;

        // Fin de simulación
        #20;
        $finish;
    end

endmodule

keyb_antirepeat.vcd
$date
	Fri Jun 20 20:37:52 2025
$end
$version
	Icarus Verilog
$end
$timescale
	1ps
$end
$scope module tb_keyb_antirepeat $end
$var wire 1 ! enable_real $end
$var reg 1 " clk $end
$var reg 1 # enable_filter $end
$var reg 1 $ reset $end
$scope module dut $end
$var wire 1 " clk $end
$var wire 1 # enable_filter $end
$var wire 1 $ reset $end
$var parameter 2 % A $end
$var parameter 2 & B $end
$var reg 2 ' curr_state [2:1] $end
$var reg 1 ! enable_real $end
$var reg 2 ( next_state [2:1] $end
$upscope $end
$upscope $end
$enddefinitions $end
$comment Show the parameter values. $end
$dumpall
b1 &
b0 %
$end
#0
$dumpvars
bx (
bx '
1$
0#
0"
x!
$end
#5000
b0 (
0!
b0 '
1"
#10000
0"
#15000
1"
0$
#20000
0"
#25000
1"
#30000
0"
#35000
b1 (
1!
1"
1#
#40000
0"
#45000
0!
b1 '
1"
#50000
0"
#55000
1"
#60000
0"
#65000
1"
#70000
0"
#75000
1"
#80000
0"
#85000
1"
#90000
0"
#95000
b0 (
1"
0#
#100000
0"
#105000
b0 '
1"
#110000
0"
#115000
b1 (
1!
1"
1#
#120000
0"
#125000
0!
b1 '
1"
