fsm_memory.v
module fsm_memory(
    input clk,
    input rst_n,
    input is_num,
    input is_op1,
    input is_op2,
    input save,
    input [3:0] num_val,
    input [3:0] res_d0,
    input [3:0] res_d1,
    input [3:0] res_d2,
    input [3:0] res_d3,
    output reg [1:0] cnt,
    output reg block,
    output reg [3:0] op1_d0,
    output reg [3:0] op1_d1,
    output reg [3:0] op1_d2,
    output reg [3:0] op1_d3,
    output reg [3:0] op2_d0,
    output reg [3:0] op2_d1,
    output reg [3:0] op2_d2,
    output reg [3:0] op2_d3
);

    reg prev_is_op1 = 0;
    reg prev_is_op2 = 0;

    reg [1:0] cnt_op1 = 0;
    reg [1:0] cnt_op2 = 0;

    always @(posedge clk or negedge rst_n) begin
        if (!rst_n) begin
            // Reset global
            op1_d0 <= 0; op1_d1 <= 0; op1_d2 <= 0; op1_d3 <= 0;
            op2_d0 <= 0; op2_d1 <= 0; op2_d2 <= 0; op2_d3 <= 0;
            cnt_op1 <= 0; cnt_op2 <= 0;
            cnt      <= 0;
            block    <= 0;
            prev_is_op1 <= 0;
            prev_is_op2 <= 0;
        end else begin

            if (save) begin
                op1_d0 <= res_d0;
                op1_d1 <= res_d1;
                op1_d2 <= res_d2;
                op1_d3 <= res_d3;
                cnt_op1 <= 2'd3;
                cnt     <= 2'd3;
                block   <= 1;
            end else begin

                // Detectar cambio de operando y resetear contadores y bloqueos
                if (is_op1 && !prev_is_op1) begin
                    op1_d0 <= 0; op1_d1 <= 0; op1_d2 <= 0; op1_d3 <= 0;
                    cnt_op1 <= 0;
                    block <= 0;
                end
                if (is_op2 && !prev_is_op2) begin
                    op2_d0 <= 0; op2_d1 <= 0; op2_d2 <= 0; op2_d3 <= 0;
                    cnt_op2 <= 0;
                    block <= 0;
                end

                // Carga manual de dígitos - importante procesar is_num siempre que block = 0
                if (is_num) begin
                    if (is_op1 && !block) begin
                        case (cnt_op1)
                            2'd0: op1_d0 <= num_val;
                            2'd1: op1_d1 <= num_val;
                            2'd2: op1_d2 <= num_val;
                            2'd3: op1_d3 <= num_val;
                        endcase
                        if (cnt_op1 < 3) cnt_op1 <= cnt_op1 + 1;
                        if (cnt_op1 == 3) block <= 1;
                        cnt <= cnt_op1;
                    end else if (is_op2 && !block) begin
                        case (cnt_op2)
                            2'd0: op2_d0 <= num_val;
                            2'd1: op2_d1 <= num_val;
                            2'd2: op2_d2 <= num_val;
                            2'd3: op2_d3 <= num_val;
                        endcase
                        if (cnt_op2 < 3) cnt_op2 <= cnt_op2 + 1;
                        if (cnt_op2 == 3) block <= 1;
                        cnt <= cnt_op2;
                    end
                end
            end

            // Guardar estados previos
            prev_is_op1 <= is_op1;
            prev_is_op2 <= is_op2;
        end
    end
endmodule

bin_BCD.v
//_________________________________________________________
//                                                         |
//                   BINARIO A BCD                         |
//             Algoritmo Double Dabble (combinacional)     |
//_________________________________________________________|
//                                                         | 
// Descripción: Módulo combinacional que convierte un      |
// número binario de 16 bits a BCD (4 dígitos).            |
// Implementa el algoritmo shift-and-add-3 (Double Dabble).|
//_________________________________________________________|
//                                                         |
// *Entradas:                                              |
//   - num_bin: número binario de 14 bits                  |
//                                                         |
// *Salidas:                                               |
//   - num_BCD: número BCD de 16 bits (4 dígitos)          |
//_________________________________________________________|

module bin_BCD(
    input wire [13:0] num_bin,
    output reg [15:0] num_BCD
);
    integer i;
    reg [29:0] shift_reg; // 16 bits binario + 12 bits para 4 dígitos BCD

    always @(*) begin
        // Inicializamos el registro con binario en los 16 bits bajos
        shift_reg = 30'b0;
        shift_reg[13:0] = num_bin;

        // Iteramos 16 veces
        for (i = 13; i >= 0; i = i - 1) begin
            // Si algún nibble BCD es >= 5, se le suma 3
            if (shift_reg[17:14] >= 5) shift_reg[17:14] = shift_reg[17:14] + 3;
            if (shift_reg[21:18] >= 5) shift_reg[21:18] = shift_reg[21:18] + 3;
            if (shift_reg[25:22] >= 5) shift_reg[25:22] = shift_reg[25:22] + 3;
            if (shift_reg[29:26] >= 5) shift_reg[29:26] = shift_reg[29:26] + 3;

            // Desplazamos todo un bit a la izquierda
            shift_reg = shift_reg << 1;
        end

        // Tomamos los 4 nibbles BCD de la parte alta
        num_BCD = shift_reg[29:14];
    end

endmodule

mux_and_bcd_converter.v
module mux_and_bcd_converter (
    input wire [13:0] res_suma_bin,
    input wire [13:0] res_resta_bin,
    input wire operator,       // Selector entre suma (1) y resta (0)
    input wire is_res,         // Selector para pasar resultado o cero

    output wire [15:0] result_bcd, // Salida BCD completa (16 bits)
    output reg [3:0] res_d3,       // Dígitos BCD individuales
    output reg [3:0] res_d2,
    output reg [3:0] res_d1,
    output reg [3:0] res_d0
);

    wire [13:0] selected_result;
    assign selected_result = (operator) ? res_suma_bin : res_resta_bin;

    wire [15:0] raw_bcd_result;

    bin_BCD bcd_converter (
        .num_bin(selected_result),
        .num_BCD(raw_bcd_result)
    );

    assign result_bcd = raw_bcd_result;

    wire [15:0] muxed_bcd_out;
    assign muxed_bcd_out = (is_res) ? raw_bcd_result : 16'b0;

    always @(*) begin
        res_d3 = muxed_bcd_out[15:12];
        res_d2 = muxed_bcd_out[11:8];
        res_d1 = muxed_bcd_out[7:4];
        res_d0 = muxed_bcd_out[3:0];
    end

endmodule

alu_core.v
module alu_core (
    input wire [13:0] op1,
    input wire [13:0] op2,
    input wire [3:0] op_val,   // 1101 suma, 1110 resta

    output reg [13:0] res_suma,
    output reg [13:0] res_resta,
    output reg f_OF,
    output reg f_sig_res
);

    // Constante decimal 9999 en binario 14 bits
    localparam MAX_DECIMAL = 14'd9999;

    wire [14:0] sum_ext = {1'b0, op1} + {1'b0, op2};  // 15 bits para posible overflow
    wire [14:0] sub_ext = {1'b0, op1} - {1'b0, op2};

    always @(*) begin
        f_OF = 0;
        f_sig_res = 0;
        res_suma = 14'd0;
        res_resta = 14'd0;

        // Suma con overflow si > 9999
        if (sum_ext > MAX_DECIMAL) begin
            f_OF = 1;
            res_suma = 14'd0;
        end else begin
            res_suma = sum_ext[13:0];
        end

        // Resta con flag de resultado negativo
        if (sub_ext[14] == 1'b1) begin
            f_sig_res = 1;
            res_resta = 14'd0;
        end else begin
            res_resta = sub_ext[13:0];
        end
    end

endmodule

BCD_bn.v
//_________________________________________________________
//                                                         |
//                        BCD-BIN                          |
//_________________________________________________________|
//                                                         | 
// Descripción: Módulo orientado a convertir números de BCD|
// a binario.                                              |
//_________________________________________________________|
// Entradas: entra un número en BCD de 16 bits (4 dígitos) |
// Salidas: sale el número en binario                     |
//_________________________________________________________|

module BCD_bn(
    input wire [15:0] num_BCD,
    output wire [13:0] num_bin  // Cambiado a 14 bits
);

    wire [3:0] unidades = num_BCD[3:0];
    wire [3:0] decenas  = num_BCD[7:4];
    wire [3:0] centenas = num_BCD[11:8];
    wire [3:0] miles    = num_BCD[15:12];

    wire [13:0] mult_10, mult_100, mult_1000;

    // Multiplicar por 10 sin función ni módulo, con 14 bits:
    assign mult_10 = ({10'b0, decenas} << 3) + ({10'b0, decenas} << 1);
    wire [13:0] temp_centenas = ({10'b0, centenas} << 3) + ({10'b0, centenas} << 1);
    assign mult_100 = (temp_centenas << 3) + (temp_centenas << 1);
    wire [13:0] temp_miles1 = ({10'b0, miles} << 3) + ({10'b0, miles} << 1);
    wire [13:0] temp_miles2 = (temp_miles1 << 3) + (temp_miles1 << 1);
    assign mult_1000 = (temp_miles2 << 3) + (temp_miles2 << 1);

    assign num_bin = {10'b0, unidades} + mult_10 + mult_100 + mult_1000;

endmodule

top.v
module top(
    input clk,
    input rst_n,
    input is_num,
    input is_op1,
    input is_op2,
    input [3:0] num_val,
    input [3:0] op_val,
    input save,

    output [15:0] op1_bin,
    output [15:0] op2_bin,
    output [15:0] alu_result_bcd,
    output f_OF,
    output f_sig_res
);

    // Dígitos operandos BCD
    wire [3:0] op1_d0, op1_d1, op1_d2, op1_d3;
    wire [3:0] op2_d0, op2_d1, op2_d2, op2_d3;

    wire [15:0] op1_bcd = {op1_d3, op1_d2, op1_d1, op1_d0};
    wire [15:0] op2_bcd = {op2_d3, op2_d2, op2_d1, op2_d0};

    // Conversión BCD a binario 14 bits
    wire [13:0] op1_bin_14;
    wire [13:0] op2_bin_14;

    BCD_bn conv_op1 (
        .num_BCD(op1_bcd),
        .num_bin(op1_bin_14)
    );

    BCD_bn conv_op2 (
        .num_BCD(op2_bcd),
        .num_bin(op2_bin_14)
    );

    // ALU Core con suma y resta
    wire [13:0] res_suma_bin, res_resta_bin;
    wire f_OF_alu, f_sig_res_alu;

    alu_core alu_inst(
        .op1(op1_bin_14),
        .op2(op2_bin_14),
        .op_val(op_val),
        .res_suma(res_suma_bin),
        .res_resta(res_resta_bin),
        .f_OF(f_OF_alu),
        .f_sig_res(f_sig_res_alu)
    );

    // Mux y conversor BCD
    wire [15:0] res_bcd;
    wire [3:0] res_d3, res_d2, res_d1, res_d0;

    mux_and_bcd_converter mux_bcd_inst(
        .res_suma_bin(res_suma_bin),
        .res_resta_bin(res_resta_bin),
        .operator(op_val == 4'b1101), // suma
        .is_res(save),
        .result_bcd(res_bcd),
        .res_d3(res_d3),
        .res_d2(res_d2),
        .res_d1(res_d1),
        .res_d0(res_d0)
    );

    // FSM memory para almacenamiento
    fsm_memory mem_inst(
        .clk(clk),
        .rst_n(rst_n),
        .is_num(is_num),
        .is_op1(is_op1),
        .is_op2(is_op2),
        .save(save),
        .num_val(num_val),
        .res_d0(res_d0),
        .res_d1(res_d1),
        .res_d2(res_d2),
        .res_d3(res_d3),
        .cnt(),
        .block(),
        .op1_d0(op1_d0),
        .op1_d1(op1_d1),
        .op1_d2(op1_d2),
        .op1_d3(op1_d3),
        .op2_d0(op2_d0),
        .op2_d1(op2_d1),
        .op2_d2(op2_d2),
        .op2_d3(op2_d3)
    );

    // Salidas para testbench o debug
    assign op1_bin = {2'b00, op1_bin_14};
    assign op2_bin = {2'b00, op2_bin_14};
    assign alu_result_bcd = res_bcd;
    assign f_OF = f_OF_alu;
    assign f_sig_res = f_sig_res_alu;

endmodule

tb_top.v
`timescale 1ns/1ps

module tb_top;

    reg clk = 0;
    reg rst_n = 0;
    reg is_num = 0;
    reg is_op1 = 0;
    reg is_op2 = 0;
    reg [3:0] num_val = 0;
    reg [3:0] op_val = 4'b1101;  // Por defecto suma
    reg save = 0;

    wire [15:0] op1_bin;
    wire [15:0] op2_bin;
    wire [15:0] alu_result_bcd;
    wire f_OF;
    wire f_sig_res;

    // Reloj 10ns período
    always #5 clk = ~clk;

    top uut (
        .clk(clk),
        .rst_n(rst_n),
        .is_num(is_num),
        .is_op1(is_op1),
        .is_op2(is_op2),
        .num_val(num_val),
        .op_val(op_val),
        .save(save),
        .op1_bin(op1_bin),
        .op2_bin(op2_bin),
        .alu_result_bcd(alu_result_bcd),
        .f_OF(f_OF),
        .f_sig_res(f_sig_res)
    );

    initial begin
        $dumpfile("tb_top.vcd");
        $dumpvars(0, tb_top);

        // Reset inicial
        rst_n = 0;
        #20;
        rst_n = 1;

        // Cargar op1 = 1,2,3,4
        is_op1 = 1; is_op2 = 0;
        is_num = 1;
        num_val = 4'd1; #10;
        num_val = 4'd2; #10;
        num_val = 4'd3; #10;
        num_val = 4'd4; #10;
        is_num = 0;

        // Cargar op2 = 5,6,7,8
        is_op1 = 0; is_op2 = 1;
        is_num = 1;
        num_val = 4'd5; #10;
        num_val = 4'd6; #10;
        num_val = 4'd7; #10;
        num_val = 4'd8; #10;
        is_num = 0;

        // Cambiar op_val a resta
        op_val = 4'b1110;

        // Guardar resultado (activar save)
        save = 1; #10;
        save = 0;

        // Cargar op1 nuevo: 5,6,7,8
        is_op1 = 1; is_op2 = 0;
        is_num = 1;
        num_val = 4'd5; #10;
        num_val = 4'd6; #10;
        num_val = 4'd7; #10;
        num_val = 4'd8; #10;
        is_num = 0;

        #50;

        $finish;
    end

    // Monitor para ver los valores en consola
    initial begin
        $monitor("Time=%0t | op1_bin=%0d | op2_bin=%0d | alu_result_bcd=%h | f_OF=%b | f_sig_res=%b",
                  $time, op1_bin, op2_bin, alu_result_bcd, f_OF, f_sig_res);
    end

endmodule

tb_top.vcd
$date
	Wed Jun 25 21:54:54 2025
$end
$version
	Icarus Verilog
$end
$timescale
	1ps
$end
$scope module tb_top $end
$var wire 16 ! op2_bin [15:0] $end
$var wire 16 " op1_bin [15:0] $end
$var wire 1 # f_sig_res $end
$var wire 1 $ f_OF $end
$var wire 16 % alu_result_bcd [15:0] $end
$var reg 1 & clk $end
$var reg 1 ' is_num $end
$var reg 1 ( is_op1 $end
$var reg 1 ) is_op2 $end
$var reg 4 * num_val [3:0] $end
$var reg 4 + op_val [3:0] $end
$var reg 1 , rst_n $end
$var reg 1 - save $end
$scope module uut $end
$var wire 16 . alu_result_bcd [15:0] $end
$var wire 1 & clk $end
$var wire 1 $ f_OF $end
$var wire 1 # f_sig_res $end
$var wire 1 ' is_num $end
$var wire 1 ( is_op1 $end
$var wire 1 ) is_op2 $end
$var wire 4 / num_val [3:0] $end
$var wire 4 0 op_val [3:0] $end
$var wire 1 , rst_n $end
$var wire 1 - save $end
$var wire 14 1 res_suma_bin [13:0] $end
$var wire 14 2 res_resta_bin [13:0] $end
$var wire 4 3 res_d3 [3:0] $end
$var wire 4 4 res_d2 [3:0] $end
$var wire 4 5 res_d1 [3:0] $end
$var wire 4 6 res_d0 [3:0] $end
$var wire 16 7 res_bcd [15:0] $end
$var wire 4 8 op2_d3 [3:0] $end
$var wire 4 9 op2_d2 [3:0] $end
$var wire 4 : op2_d1 [3:0] $end
$var wire 4 ; op2_d0 [3:0] $end
$var wire 14 < op2_bin_14 [13:0] $end
$var wire 16 = op2_bin [15:0] $end
$var wire 16 > op2_bcd [15:0] $end
$var wire 4 ? op1_d3 [3:0] $end
$var wire 4 @ op1_d2 [3:0] $end
$var wire 4 A op1_d1 [3:0] $end
$var wire 4 B op1_d0 [3:0] $end
$var wire 14 C op1_bin_14 [13:0] $end
$var wire 16 D op1_bin [15:0] $end
$var wire 16 E op1_bcd [15:0] $end
$var wire 1 F f_sig_res_alu $end
$var wire 1 G f_OF_alu $end
$scope module alu_inst $end
$var wire 4 H op_val [3:0] $end
$var wire 15 I sum_ext [14:0] $end
$var wire 15 J sub_ext [14:0] $end
$var wire 14 K op2 [13:0] $end
$var wire 14 L op1 [13:0] $end
$var parameter 14 M MAX_DECIMAL $end
$var reg 1 G f_OF $end
$var reg 1 F f_sig_res $end
$var reg 14 N res_resta [13:0] $end
$var reg 14 O res_suma [13:0] $end
$upscope $end
$scope module conv_op1 $end
$var wire 16 P num_BCD [15:0] $end
$var wire 4 Q unidades [3:0] $end
$var wire 14 R temp_miles2 [13:0] $end
$var wire 14 S temp_miles1 [13:0] $end
$var wire 14 T temp_centenas [13:0] $end
$var wire 14 U num_bin [13:0] $end
$var wire 14 V mult_1000 [13:0] $end
$var wire 14 W mult_100 [13:0] $end
$var wire 14 X mult_10 [13:0] $end
$var wire 4 Y miles [3:0] $end
$var wire 4 Z decenas [3:0] $end
$var wire 4 [ centenas [3:0] $end
$upscope $end
$scope module conv_op2 $end
$var wire 16 \ num_BCD [15:0] $end
$var wire 4 ] unidades [3:0] $end
$var wire 14 ^ temp_miles2 [13:0] $end
$var wire 14 _ temp_miles1 [13:0] $end
$var wire 14 ` temp_centenas [13:0] $end
$var wire 14 a num_bin [13:0] $end
$var wire 14 b mult_1000 [13:0] $end
$var wire 14 c mult_100 [13:0] $end
$var wire 14 d mult_10 [13:0] $end
$var wire 4 e miles [3:0] $end
$var wire 4 f decenas [3:0] $end
$var wire 4 g centenas [3:0] $end
$upscope $end
$scope module mem_inst $end
$var wire 1 & clk $end
$var wire 1 ' is_num $end
$var wire 1 ( is_op1 $end
$var wire 1 ) is_op2 $end
$var wire 4 h num_val [3:0] $end
$var wire 1 , rst_n $end
$var wire 1 - save $end
$var wire 4 i res_d3 [3:0] $end
$var wire 4 j res_d2 [3:0] $end
$var wire 4 k res_d1 [3:0] $end
$var wire 4 l res_d0 [3:0] $end
$var reg 1 m block $end
$var reg 2 n cnt [1:0] $end
$var reg 2 o cnt_op1 [1:0] $end
$var reg 2 p cnt_op2 [1:0] $end
$var reg 4 q op1_d0 [3:0] $end
$var reg 4 r op1_d1 [3:0] $end
$var reg 4 s op1_d2 [3:0] $end
$var reg 4 t op1_d3 [3:0] $end
$var reg 4 u op2_d0 [3:0] $end
$var reg 4 v op2_d1 [3:0] $end
$var reg 4 w op2_d2 [3:0] $end
$var reg 4 x op2_d3 [3:0] $end
$var reg 1 y prev_is_op1 $end
$var reg 1 z prev_is_op2 $end
$upscope $end
$scope module mux_bcd_inst $end
$var wire 1 - is_res $end
$var wire 1 { operator $end
$var wire 14 | res_resta_bin [13:0] $end
$var wire 14 } res_suma_bin [13:0] $end
$var wire 16 ~ result_bcd [15:0] $end
$var wire 14 !" selected_result [13:0] $end
$var wire 16 "" raw_bcd_result [15:0] $end
$var wire 16 #" muxed_bcd_out [15:0] $end
$var reg 4 $" res_d0 [3:0] $end
$var reg 4 %" res_d1 [3:0] $end
$var reg 4 &" res_d2 [3:0] $end
$var reg 4 '" res_d3 [3:0] $end
$scope module bcd_converter $end
$var wire 14 (" num_bin [13:0] $end
$var reg 16 )" num_BCD [15:0] $end
$var reg 30 *" shift_reg [29:0] $end
$var integer 32 +" i [31:0] $end
$upscope $end
$upscope $end
$upscope $end
$upscope $end
$enddefinitions $end
$comment Show the parameter values. $end
$dumpall
b10011100001111 M
$end
#0
$dumpvars
bx +"
bx *"
bx )"
bx ("
b0 '"
b0 &"
b0 %"
b0 $"
b0 #"
bx ""
bx !"
bx ~
bx }
bx |
1{
0z
0y
bx x
bx w
bx v
bx u
bx t
bx s
bx r
bx q
b0 p
b0 o
bx n
xm
b0 l
b0 k
b0 j
b0 i
b0 h
bx g
bx f
bx e
bx d
bx c
bx b
bx a
bx `
bx _
bx ^
bx ]
bx \
bx [
bx Z
bx Y
bx X
bx W
bx V
bx U
bx T
bx S
bx R
bx Q
bx P
bx O
bx N
bx L
bx K
bx J
bx I
b1101 H
xG
xF
bx E
b0xxxxxxxxxxxxxx D
bx C
bx B
bx A
bx @
bx ?
bx >
b0xxxxxxxxxxxxxx =
bx <
bx ;
bx :
bx 9
bx 8
bx 7
b0 6
b0 5
b0 4
b0 3
bx 2
bx 1
b1101 0
b0 /
bx .
0-
0,
b1101 +
b0 *
0)
0(
0'
0&
bx %
x$
x#
b0xxxxxxxxxxxxxx "
b0xxxxxxxxxxxxxx !
$end
#5000
b0 %
b0 .
b0 7
b0 ~
b0 ""
b0 )"
b11111111111111111111111111111111 +"
b0 *"
b0 !"
b0 ("
b0 2
b0 N
b0 |
b0 1
b0 O
b0 }
0#
0F
0$
0G
b0 J
b0 I
b0 !
b0 =
b0 <
b0 K
b0 a
b0 b
b0 "
b0 D
b0 C
b0 L
b0 U
b0 V
b0 ^
b0 c
b0 R
b0 W
b0 _
b0 `
b0 d
b0 S
b0 T
b0 X
b0 e
b0 g
b0 f
b0 ]
b0 Y
b0 [
b0 Z
b0 Q
0m
b0 n
b0 8
b0 x
b0 9
b0 w
b0 :
b0 v
b0 >
b0 \
b0 ;
b0 u
b0 ?
b0 t
b0 @
b0 s
b0 A
b0 r
b0 E
b0 P
b0 B
b0 q
1&
#10000
0&
#15000
1&
#20000
0&
b1 *
b1 /
b1 h
1'
1(
1,
#25000
b1 %
b1 .
b1 7
b1 ~
b1 ""
b1 )"
b11111111111111111111111111111111 +"
b100000000000000 *"
b1 !"
b1 ("
b1 2
b1 N
b1 |
b1 1
b1 O
b1 }
b1 J
b1 I
b1 "
b1 D
b1 C
b1 L
b1 U
b1 Q
1y
b1 o
b1 E
b1 P
b1 B
b1 q
1&
#30000
0&
b10 *
b10 /
b10 h
#35000
b100001 %
b100001 .
b100001 7
b100001 ~
b100001 ""
b100001 )"
b11111111111111111111111111111111 +"
b10000100000000000000 *"
b10101 !"
b10101 ("
b10101 2
b10101 N
b10101 |
b10101 1
b10101 O
b10101 }
b10101 J
b10101 I
b10101 "
b10101 D
b10101 C
b10101 L
b10101 U
b10100 X
b10 Z
b1 n
b10 o
b100001 E
b100001 P
b10 A
b10 r
1&
#40000
0&
b11 *
b11 /
b11 h
#45000
b1100100001 %
b1100100001 .
b1100100001 7
b1100100001 ~
b1100100001 ""
b1100100001 )"
b11111111111111111111111111111111 +"
b110010000100000000000000 *"
b101000001 !"
b101000001 ("
b101000001 2
b101000001 N
b101000001 |
b101000001 1
b101000001 O
b101000001 }
b101000001 J
b101000001 I
b101000001 "
b101000001 D
b101000001 C
b101000001 L
b101000001 U
b100101100 W
b11110 T
b11 [
b10 n
b11 o
b1100100001 E
b1100100001 P
b11 @
b11 s
1&
#50000
0&
b100 *
b100 /
b100 h
#55000
b100001100100001 %
b100001100100001 .
b100001100100001 7
b100001100100001 ~
b100001100100001 ""
b100001100100001 )"
b11111111111111111111111111111111 +"
b10000110010000100000000000000 *"
b1000011100001 !"
b1000011100001 ("
b1000011100001 2
b1000011100001 N
b1000011100001 |
b1000011100001 1
b1000011100001 O
b1000011100001 }
b1000011100001 J
b1000011100001 I
b1000011100001 "
b1000011100001 D
b1000011100001 C
b1000011100001 L
b1000011100001 U
b111110100000 V
b110010000 R
b101000 S
b100 Y
b11 n
1m
b100001100100001 E
b100001100100001 P
b100 ?
b100 t
1&
#60000
0&
b101 *
b101 /
b101 h
1)
0(
1'
#65000
1z
0y
0m
1&
#70000
0&
b110 *
b110 /
b110 h
#75000
b100001100100111 %
b100001100100111 .
b100001100100111 7
b100001100100111 ~
b100001100100111 ""
b100001100100111 )"
b11111111111111111111111111111111 +"
b10000110010011100000000000000 *"
b1000011100111 !"
b1000011100111 ("
b1000011011011 2
b1000011011011 N
b1000011011011 |
b1000011100111 1
b1000011100111 O
b1000011100111 }
b1000011011011 J
b1000011100111 I
b110 !
b110 =
b110 <
b110 K
b110 a
b110 ]
b0 n
b1 p
b110 >
b110 \
b110 ;
b110 u
1&
#80000
0&
b111 *
b111 /
b111 h
#85000
b100001110010111 %
b100001110010111 .
b100001110010111 7
b100001110010111 ~
b100001110010111 ""
b100001110010111 )"
b11111111111111111111111111111111 +"
b10000111001011100000000000000 *"
b1000100101101 !"
b1000100101101 ("
b1000010010101 2
b1000010010101 N
b1000010010101 |
b1000100101101 1
b1000100101101 O
b1000100101101 }
b1000010010101 J
b1000100101101 I
b1001100 !
b1001100 =
b1001100 <
b1001100 K
b1001100 a
b1000110 d
b111 f
b1 n
b10 p
b1110110 >
b1110110 \
b111 :
b111 v
1&
#90000
0&
b1000 *
b1000 /
b1000 h
#95000
b101000110010111 %
b101000110010111 .
b101000110010111 7
b101000110010111 ~
b101000110010111 ""
b101000110010111 )"
b11111111111111111111111111111111 +"
b10100011001011100000000000000 *"
b1010001001101 !"
b1010001001101 ("
b110101110101 2
b110101110101 N
b110101110101 |
b1010001001101 1
b1010001001101 O
b1010001001101 }
b110101110101 J
b1010001001101 I
b1101101100 !
b1101101100 =
b1101101100 <
b1101101100 K
b1101101100 a
b1100100000 c
b1010000 `
b1000 g
b10 n
b11 p
b100001110110 >
b100001110110 \
b1000 9
b1000 w
1&
#100000
b101 6
b101 l
b101 $"
b100 5
b100 k
b100 %"
b100 4
b100 j
b100 &"
b11 3
b11 i
b11 '"
b11010001000101 %
b11010001000101 .
b11010001000101 7
b11010001000101 ~
b11010001000101 ""
b11010001000101 )"
b11111111111111111111111111111111 +"
b1101000100010100000000000000 *"
b11010001000101 #"
b110101110101 !"
b110101110101 ("
0&
1-
0{
b1110 +
b1110 0
b1110 H
0'
#105000
b10 3
b10 i
b10 '"
b101 4
b101 j
b101 &"
b110 5
b110 k
b110 %"
b1001 6
b1001 l
b1001 $"
b10010101101001 #"
b101110111000 V
b10010101101001 %
b10010101101001 .
b10010101101001 7
b10010101101001 ~
b10010101101001 ""
b10010101101001 )"
b11111111111111111111111111111111 +"
b1001010110100100000000000000 *"
b100101100 R
b110010000 W
b101000001001 !"
b101000001001 ("
b11110 S
b101000 T
b101000 X
b101000001001 2
b101000001001 N
b101000001001 |
b1000011100001 1
b1000011100001 O
b1000011100001 }
b11 Y
b100 [
b100 Z
b101000001001 J
b1000011100001 I
b110101110101 "
b110101110101 D
b110101110101 C
b110101110101 L
b110101110101 U
b101 Q
1m
b11 n
b11 ?
b11 t
b100 @
b100 s
b100 A
b100 r
b11010001000101 E
b11010001000101 P
b101 B
b101 q
1&
#110000
b0 6
b0 l
b0 $"
b0 5
b0 k
b0 %"
b0 4
b0 j
b0 &"
b0 3
b0 i
b0 '"
b0 #"
0&
b101 *
b101 /
b101 h
1'
0)
1(
0-
#115000
1#
1F
b0 V
b0 %
b0 .
b0 7
b0 ~
b0 ""
b0 )"
b11111111111111111111111111111111 +"
b0 *"
b0 R
b0 W
b0 !"
b0 ("
b0 S
b0 T
b0 X
b0 2
b0 N
b0 |
b1101101100 1
b1101101100 O
b1101101100 }
b0 Y
b0 [
b0 Z
b111110010010100 J
b1101101100 I
b0 "
b0 D
b0 C
b0 L
b0 U
b0 Q
0z
1y
0m
b0 o
b0 ?
b0 t
b0 @
b0 s
b0 A
b0 r
b0 E
b0 P
b0 B
b0 q
1&
#120000
0&
b110 *
b110 /
b110 h
#125000
b1101110010 1
b1101110010 O
b1101110010 }
1#
1F
b111110010011010 J
b1101110010 I
b110 "
b110 D
b110 C
b110 L
b110 U
b110 Q
b0 n
b1 o
b110 E
b110 P
b110 B
b110 q
1&
#130000
0&
b111 *
b111 /
b111 h
#135000
b1110111000 1
b1110111000 O
b1110111000 }
1#
1F
b111110011100000 J
b1110111000 I
b1001100 "
b1001100 D
b1001100 C
b1001100 L
b1001100 U
b1000110 X
b111 Z
b1 n
b10 o
b1110110 E
b1110110 P
b111 A
b111 r
1&
#140000
0&
b1000 *
b1000 /
b1000 h
#145000
b11011011000 1
b11011011000 O
b11011011000 }
0#
0F
b0 J
b11011011000 I
b1101101100 "
b1101101100 D
b1101101100 C
b1101101100 L
b1101101100 U
b1100100000 W
b1010000 T
b1000 [
b10 n
b11 o
b100001110110 E
b100001110110 P
b1000 @
b1000 s
1&
#150000
0&
0'
